Workbook

Sheet dashboard
A1: SALES PERFORMANCE DASHBOARD
A3: Reporting Period | B3: 1-14 September 2025
A5: KEY PERFORMANCE INDICATORS
A7: Total Recorded Revenue | C7: Total Orders | E7: Average Revenue per Known Order | G7: Total Quantity Sold
A8: =SUM(SalesData[Revenue]) -> 256000 | C8: =COUNTA(SalesData[Order ID]) -> 15 | E8: =AVERAGE(SalesData[Revenue]) -> 18285.714 | G8: =SUM(SalesData[Quantity]) -> 31
A11: Region | B11: Revenue | D11: Payment Method | E11: Revenue
A12: Abuja | B12: =SUMIF(SalesData[Region],A12,SalesData[Revenue]) -> 178000 | D12: Cash | E12: =SUMIF(SalesData[Payment Method],D12,SalesData[Revenue]) -> 52000
A13: Lagos | B13: =SUMIF(SalesData[Region],A13,SalesData[Revenue]) -> 78000 | D13: Card | E13: =SUMIF(SalesData[Payment Method],D13,SalesData[Revenue]) -> 132000
D14: Transfer | E14: =SUMIF(SalesData[Payment Method],D14,SalesData[Revenue]) -> 72000
A32: Data-quality note:
A33: Order ORD009 has a missing quantity. Its revenue is excluded from the recorded total of ₦256,000. The average revenue of ₦18,285.71 is based on 14 orders with known revenue, not all 15 orders.

Sheet raw data
A1: Order ID | B1: Date | C1: Customer | D1: Product | E1: Category | F1: Quantity | G1: Unit Price | H1: Region | I1: Payment Method
A2: ORD001 | B2: 46266 | C2: Ada | D2: Laptop bag | E2: Accessories | F2: 2 | G2: 15000 | H2: Abuja | I2: Card
A3: ORD002 | B3: 46267 | C3: Chinedu | D3: Mouse | E3: Electronics | F3: 3 | G3: 5000 | H3: Lagos | I3: Transfer
A4: ORD003 | B4: 46267 | C4: Amaka | D4: Keyboard | E4: Electronics | F4: 1 | G4: 12000 | H4: Abuja | I4: Cash
A5: ORD004 | B5: 46268 | C5: David | D5: Laptop bag | E5: Accessories | F5: 1 | G5: 15000 | H5: lagos | I5: Transfer
A6: ORD005 | B6: 46269 | C6: Esther | D6: Headphones | E6: Electronics | F6: 2 | G6: 18000 | H6: Abuja | I6: Card
A7: ORD006 | B7: 46270 | C7: Favour | D7: USB Cable | E7: Accessories | F7: 5 | G7: 3000 | H7: Abuja | I7: transfer
A8: ORD007 | B8: 46271 | C8: Grace | D8: Mouse | E8: Electronics | F8: 2 | G8: 5000 | H8: Lagos | I8: Cash
A9: ORD008 | B9: 46272 | C9: Ibrahim | D9: Keyboard | E9: Electronics | F9: 1 | G9: 12000 | H9: Abuja | I9: Card
A10: ORD009 | B10: 46273 | C10: Jane | D10: Headphones | E10: Electronics | G10: 18000 | H10: Lagos | I10: Transfer
A11: ORD010 | B11: 46274 | C11: Kelechi | D11: Laptop bag | E11: Accessories | F11: 2 | G11: 15000 | H11: Abuja | I11: Card
A12: ORD011 | B12: 46275 | C12: Mary | D12: Mouse | E12: Electronics | F12: 4 | G12: 5000 | H12: Lagos | I12: Cash
A13: ORD012 | B13: 46276 | C13: Nneka | D13: USB Cable | E13: Accessories | F13: 3 | G13: 3000 | H13: Abuja | I13: Transfer
A14: ORD013 | B14: 46277 | C14: Obi | D14: Keyboard | E14: Electronics | F14: 2 | G14: 12000 | H14: Abuja | I14: Card
A15: ORD014 | B15: 46278 | C15: Peter | D15: Headphones | E15: Electronics | F15: 1 | G15: 18000 | H15: Lagos | I15: Transfer
A16: ORD015 | B16: 46279 | C16: Rita | D16: Mouse | E16: Electronics | F16: 2 | G16: 5000 | H16: Abuja | I16: Cash
A17: ORD015 | B17: 46279 | C17: Rita | D17: Mouse | E17: Electronics | F17: 2 | G17: 5000 | H17: Abuja | I17: Cash

Sheet clean data
A1: Order ID | B1: Date | C1: Customer | D1: Product | E1: Category | F1: Quantity | G1: Unit Price | H1: Region | I1: Payment Method | J1: Revenue | K1: Data Status | L1: Lookup Price
A2: ORD001 | B2: 46266 | C2: Ada | D2: Laptop bag | E2: Accessories | F2: 2 | G2: 15000 | H2: Abuja | I2: Card | J2: =SUM(F2*G2) -> 30000 | K2: =IF(SalesData[[#This Row],[Quantity]]="", "Missing quantity", "Complete") -> Complete | L2: =VLOOKUP(SalesData[[#This Row],[Product]],'price list'!$A$2:$B$6,2,FALSE) -> 15000
A3: ORD002 | B3: 46267 | C3: Chinedu | D3: Mouse | E3: Electronics | F3: 3 | G3: 5000 | H3: Lagos | I3: Transfer | J3: =SUM(F3*G3) -> 15000 | K3: =IF(SalesData[[#This Row],[Quantity]]="", "Missing quantity", "Complete") -> Complete | L3: =VLOOKUP(SalesData[[#This Row],[Product]],'price list'!$A$2:$B$6,2,FALSE) -> 5000
A4: ORD003 | B4: 46267 | C4: Amaka | D4: Keyboard | E4: Electronics | F4: 1 | G4: 12000 | H4: Abuja | I4: Cash | J4: =SUM(F4*G4) -> 12000 | K4: =IF(SalesData[[#This Row],[Quantity]]="", "Missing quantity", "Complete") -> Complete | L4: =VLOOKUP(SalesData[[#This Row],[Product]],'price list'!$A$2:$B$6,2,FALSE) -> 12000
A5: ORD004 | B5: 46268 | C5: David | D5: Laptop bag | E5: Accessories | F5: 1 | G5: 15000 | H5: Lagos | I5: Transfer | J5: =SUM(F5*G5) -> 15000 | K5: =IF(SalesData[[#This Row],[Quantity]]="", "Missing quantity", "Complete") -> Complete | L5: =VLOOKUP(SalesData[[#This Row],[Product]],'price list'!$A$2:$B$6,2,FALSE) -> 15000
A6: ORD005 | B6: 46269 | C6: Esther | D6: Headphones | E6: Electronics | F6: 2 | G6: 18000 | H6: Abuja | I6: Card | J6: =SUM(F6*G6) -> 36000 | K6: =IF(SalesData[[#This Row],[Quantity]]="", "Missing quantity", "Complete") -> Complete | L6: =VLOOKUP(SalesData[[#This Row],[Product]],'price list'!$A$2:$B$6,2,FALSE) -> 18000
A7: ORD006 | B7: 46270 | C7: Favour | D7: USB Cable | E7: Accessories | F7: 5 | G7: 3000 | H7: Abuja | I7: Transfer | J7: =SUM(F7*G7) -> 15000 | K7: =IF(SalesData[[#This Row],[Quantity]]="", "Missing quantity", "Complete") -> Complete | L7: =VLOOKUP(SalesData[[#This Row],[Product]],'price list'!$A$2:$B$6,2,FALSE) -> 3000
A8: ORD007 | B8: 46271 | C8: Grace | D8: Mouse | E8: Electronics | F8: 2 | G8: 5000 | H8: Lagos | I8: Cash | J8: =SUM(F8*G8) -> 10000 | K8: =IF(SalesData[[#This Row],[Quantity]]="", "Missing quantity", "Complete") -> Complete | L8: =VLOOKUP(SalesData[[#This Row],[Product]],'price list'!$A$2:$B$6,2,FALSE) -> 5000
A9: ORD008 | B9: 46272 | C9: Ibrahim | D9: Keyboard | E9: Electronics | F9: 1 | G9: 12000 | H9: Abuja | I9: Card | J9: =SUM(F9*G9) -> 12000 | K9: =IF(SalesData[[#This Row],[Quantity]]="", "Missing quantity", "Complete") -> Complete | L9: =VLOOKUP(SalesData[[#This Row],[Product]],'price list'!$A$2:$B$6,2,FALSE) -> 12000
A10: ORD009 | B10: 46273 | C10: Jane | D10: Headphones | E10: Electronics | G10: 18000 | H10: Lagos | I10: Transfer | K10: =IF(SalesData[[#This Row],[Quantity]]="", "Missing quantity", "Complete") -> Missing quantity | L10: =VLOOKUP(SalesData[[#This Row],[Product]],'price list'!$A$2:$B$6,2,FALSE) -> 18000
A11: ORD010 | B11: 46274 | C11: Kelechi | D11: Laptop bag | E11: Accessories | F11: 2 | G11: 15000 | H11: Abuja | I11: Card | J11: =SUM(F11*G11) -> 30000 | K11: =IF(SalesData[[#This Row],[Quantity]]="", "Missing quantity", "Complete") -> Complete | L11: =VLOOKUP(SalesData[[#This Row],[Product]],'price list'!$A$2:$B$6,2,FALSE) -> 15000
A12: ORD011 | B12: 46275 | C12: Mary | D12: Mouse | E12: Electronics | F12: 4 | G12: 5000 | H12: Lagos | I12: Cash | J12: =SUM(F12*G12) -> 20000 | K12: =IF(SalesData[[#This Row],[Quantity]]="", "Missing quantity", "Complete") -> Complete | L12: =VLOOKUP(SalesData[[#This Row],[Product]],'price list'!$A$2:$B$6,2,FALSE) -> 5000
A13: ORD012 | B13: 46276 | C13: Nneka | D13: USB Cable | E13: Accessories | F13: 3 | G13: 3000 | H13: Abuja | I13: Transfer | J13: =SUM(F13*G13) -> 9000 | K13: =IF(SalesData[[#This Row],[Quantity]]="", "Missing quantity", "Complete") -> Complete | L13: =VLOOKUP(SalesData[[#This Row],[Product]],'price list'!$A$2:$B$6,2,FALSE) -> 3000
A14: ORD013 | B14: 46277 | C14: Obi | D14: Keyboard | E14: Electronics | F14: 2 | G14: 12000 | H14: Abuja | I14: Card | J14: =SUM(F14*G14) -> 24000 | K14: =IF(SalesData[[#This Row],[Quantity]]="", "Missing quantity", "Complete") -> Complete | L14: =VLOOKUP(SalesData[[#This Row],[Product]],'price list'!$A$2:$B$6,2,FALSE) -> 12000
A15: ORD014 | B15: 46278 | C15: Peter | D15: Headphones | E15: Electronics | F15: 1 | G15: 18000 | H15: Lagos | I15: Transfer | J15: =SUM(F15*G15) -> 18000 | K15: =IF(SalesData[[#This Row],[Quantity]]="", "Missing quantity", "Complete") -> Complete | L15: =VLOOKUP(SalesData[[#This Row],[Product]],'price list'!$A$2:$B$6,2,FALSE) -> 18000
A16: ORD015 | B16: 46279 | C16: Rita | D16: Mouse | E16: Electronics | F16: 2 | G16: 5000 | H16: Abuja | I16: Cash | J16: =SUM(F16*G16) -> 10000 | K16: =IF(SalesData[[#This Row],[Quantity]]="", "Missing quantity", "Complete") -> Complete | L16: =VLOOKUP(SalesData[[#This Row],[Product]],'price list'!$A$2:$B$6,2,FALSE) -> 5000

Sheet cleaning notes
A1: Issue | B1: Column | C1: Action
A2: Duplicate record | B2: Order ID | C2: Removed Duplicate ORD15
A3: Missing Value | B3: Quantity | C3: Flagged for investigation
A4: Inconsistent Capitalization | B4: Region | C4: Standardize
A5: Inconsistent Capitalization | B5: Payment Method | C5: Standardize

Sheet sales data
A1: Order ID | B1: Date | C1: Customer | D1: Product | E1: Category | F1: Quantity | G1: Unit Price | H1: Region | I1: Payment Method | J1: Revenue | K1: Data Status | L1: Lookup Price | M1: Duplicate Check | N1: Payment Check
A2: ORD001 | B2: 46266 | C2: Ada | D2: Laptop bag | E2: Accessories | F2: 2 | G2: 15000 | H2: Abuja | I2: Card | J2: =SUM(F2*G2) -> 30000 | K2: =IF(SalesData3[[#This Row],[Quantity]]="", "Missing quantity", "Complete") -> Complete | L2: =VLOOKUP(SalesData3[[#This Row],[Product]],'price list'!$A$2:$B$6,2,FALSE) -> 15000 | M2: =COUNTIF(SalesData[Order ID],SalesData[[#This Row],[Order ID]]) -> 1 | N2: =IF(OR(SalesData3[[#This Row],[Payment Method]]="Cash",SalesData3[[#This Row],[Payment Method]]="Card",SalesData3[[#This Row],[Payment Method]]="Transfer"),"Valid", "Invalid") -> Valid
A3: ORD002 | B3: 46267 | C3: Chinedu | D3: Mouse | E3: Electronics | F3: 3 | G3: 5000 | H3: Lagos | I3: Transfer | J3: =SUM(F3*G3) -> 15000 | K3: =IF(SalesData3[[#This Row],[Quantity]]="", "Missing quantity", "Complete") -> Complete | L3: =VLOOKUP(SalesData3[[#This Row],[Product]],'price list'!$A$2:$B$6,2,FALSE) -> 5000 | M3: =COUNTIF(SalesData[Order ID],SalesData[[#This Row],[Order ID]]) -> 1 | N3: =IF(OR(SalesData3[[#This Row],[Payment Method]]="Cash",SalesData3[[#This Row],[Payment Method]]="Card",SalesData3[[#This Row],[Payment Method]]="Transfer"),"Valid", "Invalid") -> Valid
A4: ORD003 | B4: 46267 | C4: Amaka | D4: Keyboard | E4: Electronics | F4: 1 | G4: 12000 | H4: Abuja | I4: Cash | J4: =SUM(F4*G4) -> 12000 | K4: =IF(SalesData3[[#This Row],[Quantity]]="", "Missing quantity", "Complete") -> Complete | L4: =VLOOKUP(SalesData3[[#This Row],[Product]],'price list'!$A$2:$B$6,2,FALSE) -> 12000 | M4: =COUNTIF(SalesData[Order ID],SalesData[[#This Row],[Order ID]]) -> 1 | N4: =IF(OR(SalesData3[[#This Row],[Payment Method]]="Cash",SalesData3[[#This Row],[Payment Method]]="Card",SalesData3[[#This Row],[Payment Method]]="Transfer"),"Valid", "Invalid") -> Valid
A5: ORD004 | B5: 46268 | C5: David | D5: Laptop bag | E5: Accessories | F5: 1 | G5: 15000 | H5: Lagos | I5: Transfer | J5: =SUM(F5*G5) -> 15000 | K5: =IF(SalesData3[[#This Row],[Quantity]]="", "Missing quantity", "Complete") -> Complete | L5: =VLOOKUP(SalesData3[[#This Row],[Product]],'price list'!$A$2:$B$6,2,FALSE) -> 15000 | M5: =COUNTIF(SalesData[Order ID],SalesData[[#This Row],[Order ID]]) -> 1 | N5: =IF(OR(SalesData3[[#This Row],[Payment Method]]="Cash",SalesData3[[#This Row],[Payment Method]]="Card",SalesData3[[#This Row],[Payment Method]]="Transfer"),"Valid", "Invalid") -> Valid
A6: ORD005 | B6: 46269 | C6: Esther | D6: Headphones | E6: Electronics | F6: 2 | G6: 18000 | H6: Abuja | I6: Card | J6: =SUM(F6*G6) -> 36000 | K6: =IF(SalesData3[[#This Row],[Quantity]]="", "Missing quantity", "Complete") -> Complete | L6: =VLOOKUP(SalesData3[[#This Row],[Product]],'price list'!$A$2:$B$6,2,FALSE) -> 18000 | M6: =COUNTIF(SalesData[Order ID],SalesData[[#This Row],[Order ID]]) -> 1 | N6: =IF(OR(SalesData3[[#This Row],[Payment Method]]="Cash",SalesData3[[#This Row],[Payment Method]]="Card",SalesData3[[#This Row],[Payment Method]]="Transfer"),"Valid", "Invalid") -> Valid
A7: ORD006 | B7: 46270 | C7: Favour | D7: USB Cable | E7: Accessories | F7: 5 | G7: 3000 | H7: Abuja | I7: Transfer | J7: =SUM(F7*G7) -> 15000 | K7: =IF(SalesData3[[#This Row],[Quantity]]="", "Missing quantity", "Complete") -> Complete | L7: =VLOOKUP(SalesData3[[#This Row],[Product]],'price list'!$A$2:$B$6,2,FALSE) -> 3000 | M7: =COUNTIF(SalesData[Order ID],SalesData[[#This Row],[Order ID]]) -> 1 | N7: =IF(OR(SalesData3[[#This Row],[Payment Method]]="Cash",SalesData3[[#This Row],[Payment Method]]="Card",SalesData3[[#This Row],[Payment Method]]="Transfer"),"Valid", "Invalid") -> Valid
A8: ORD007 | B8: 46271 | C8: Grace | D8: Mouse | E8: Electronics | F8: 2 | G8: 5000 | H8: Lagos | I8: Cash | J8: =SUM(F8*G8) -> 10000 | K8: =IF(SalesData3[[#This Row],[Quantity]]="", "Missing quantity", "Complete") -> Complete | L8: =VLOOKUP(SalesData3[[#This Row],[Product]],'price list'!$A$2:$B$6,2,FALSE) -> 5000 | M8: =COUNTIF(SalesData[Order ID],SalesData[[#This Row],[Order ID]]) -> 1 | N8: =IF(OR(SalesData3[[#This Row],[Payment Method]]="Cash",SalesData3[[#This Row],[Payment Method]]="Card",SalesData3[[#This Row],[Payment Method]]="Transfer"),"Valid", "Invalid") -> Valid
A9: ORD008 | B9: 46272 | C9: Ibrahim | D9: Keyboard | E9: Electronics | F9: 1 | G9: 12000 | H9: Abuja | I9: Card | J9: =SUM(F9*G9) -> 12000 | K9: =IF(SalesData3[[#This Row],[Quantity]]="", "Missing quantity", "Complete") -> Complete | L9: =VLOOKUP(SalesData3[[#This Row],[Product]],'price list'!$A$2:$B$6,2,FALSE) -> 12000 | M9: =COUNTIF(SalesData[Order ID],SalesData[[#This Row],[Order ID]]) -> 1 | N9: =IF(OR(SalesData3[[#This Row],[Payment Method]]="Cash",SalesData3[[#This Row],[Payment Method]]="Card",SalesData3[[#This Row],[Payment Method]]="Transfer"),"Valid", "Invalid") -> Valid
A10: ORD009 | B10: 46273 | C10: Jane | D10: Headphones | E10: Electronics | G10: 18000 | H10: Lagos | I10: Transfer | K10: =IF(SalesData3[[#This Row],[Quantity]]="", "Missing quantity", "Complete") -> Missing quantity | L10: =VLOOKUP(SalesData3[[#This Row],[Product]],'price list'!$A$2:$B$6,2,FALSE) -> 18000 | M10: =COUNTIF(SalesData[Order ID],SalesData[[#This Row],[Order ID]]) -> 1 | N10: =IF(OR(SalesData3[[#This Row],[Payment Method]]="Cash",SalesData3[[#This Row],[Payment Method]]="Card",SalesData3[[#This Row],[Payment Method]]="Transfer"),"Valid", "Invalid") -> Valid
A11: ORD010 | B11: 46274 | C11: Kelechi | D11: Laptop bag | E11: Accessories | F11: 2 | G11: 15000 | H11: Abuja | I11: Card | J11: =SUM(F11*G11) -> 30000 | K11: =IF(SalesData3[[#This Row],[Quantity]]="", "Missing quantity", "Complete") -> Complete | L11: =VLOOKUP(SalesData3[[#This Row],[Product]],'price list'!$A$2:$B$6,2,FALSE) -> 15000 | M11: =COUNTIF(SalesData[Order ID],SalesData[[#This Row],[Order ID]]) -> 1 | N11: =IF(OR(SalesData3[[#This Row],[Payment Method]]="Cash",SalesData3[[#This Row],[Payment Method]]="Card",SalesData3[[#This Row],[Payment Method]]="Transfer"),"Valid", "Invalid") -> Valid
A12: ORD011 | B12: 46275 | C12: Mary | D12: Mouse | E12: Electronics | F12: 4 | G12: 5000 | H12: Lagos | I12: Cash | J12: =SUM(F12*G12) -> 20000 | K12: =IF(SalesData3[[#This Row],[Quantity]]="", "Missing quantity", "Complete") -> Complete | L12: =VLOOKUP(SalesData3[[#This Row],[Product]],'price list'!$A$2:$B$6,2,FALSE) -> 5000 | M12: =COUNTIF(SalesData[Order ID],SalesData[[#This Row],[Order ID]]) -> 1 | N12: =IF(OR(SalesData3[[#This Row],[Payment Method]]="Cash",SalesData3[[#This Row],[Payment Method]]="Card",SalesData3[[#This Row],[Payment Method]]="Transfer"),"Valid", "Invalid") -> Valid
A13: ORD012 | B13: 46276 | C13: Nneka | D13: USB Cable | E13: Accessories | F13: 3 | G13: 3000 | H13: Abuja | I13: Transfer | J13: =SUM(F13*G13) -> 9000 | K13: =IF(SalesData3[[#This Row],[Quantity]]="", "Missing quantity", "Complete") -> Complete | L13: =VLOOKUP(SalesData3[[#This Row],[Product]],'price list'!$A$2:$B$6,2,FALSE) -> 3000 | M13: =COUNTIF(SalesData[Order ID],SalesData[[#This Row],[Order ID]]) -> 1 | N13: =IF(OR(SalesData3[[#This Row],[Payment Method]]="Cash",SalesData3[[#This Row],[Payment Method]]="Card",SalesData3[[#This Row],[Payment Method]]="Transfer"),"Valid", "Invalid") -> Valid
A14: ORD013 | B14: 46277 | C14: Obi | D14: Keyboard | E14: Electronics | F14: 2 | G14: 12000 | H14: Abuja | I14: Card | J14: =SUM(F14*G14) -> 24000 | K14: =IF(SalesData3[[#This Row],[Quantity]]="", "Missing quantity", "Complete") -> Complete | L14: =VLOOKUP(SalesData3[[#This Row],[Product]],'price list'!$A$2:$B$6,2,FALSE) -> 12000 | M14: =COUNTIF(SalesData[Order ID],SalesData[[#This Row],[Order ID]]) -> 1 | N14: =IF(OR(SalesData3[[#This Row],[Payment Method]]="Cash",SalesData3[[#This Row],[Payment Method]]="Card",SalesData3[[#This Row],[Payment Method]]="Transfer"),"Valid", "Invalid") -> Valid
A15: ORD014 | B15: 46278 | C15: Peter | D15: Headphones | E15: Electronics | F15: 1 | G15: 18000 | H15: Lagos | I15: Transfer | J15: =SUM(F15*G15) -> 18000 | K15: =IF(SalesData3[[#This Row],[Quantity]]="", "Missing quantity", "Complete") -> Complete | L15: =VLOOKUP(SalesData3[[#This Row],[Product]],'price list'!$A$2:$B$6,2,FALSE) -> 18000 | M15: =COUNTIF(SalesData[Order ID],SalesData[[#This Row],[Order ID]]) -> 1 | N15: =IF(OR(SalesData3[[#This Row],[Payment Method]]="Cash",SalesData3[[#This Row],[Payment Method]]="Card",SalesData3[[#This Row],[Payment Method]]="Transfer"),"Valid", "Invalid") -> Valid
A16: ORD015 | B16: 46279 | C16: Rita | D16: Mouse | E16: Electronics | F16: 2 | G16: 5000 | H16: Abuja | I16: Cash | J16: =SUM(F16*G16) -> 10000 | K16: =IF(SalesData3[[#This Row],[Quantity]]="", "Missing quantity", "Complete") -> Complete | L16: =VLOOKUP(SalesData3[[#This Row],[Product]],'price list'!$A$2:$B$6,2,FALSE) -> 5000 | M16: =COUNTIF(SalesData[Order ID],SalesData[[#This Row],[Order ID]]) -> 1 | N16: =IF(OR(SalesData3[[#This Row],[Payment Method]]="Cash",SalesData3[[#This Row],[Payment Method]]="Card",SalesData3[[#This Row],[Payment Method]]="Transfer"),"Valid", "Invalid") -> Valid
F17: =SUBTOTAL(109,SalesData3[Quantity]) -> 31 | J17: =SUM(SalesData3[Revenue]) -> 256000
I18: Abuja Revenue | J18: =SUMIF(SalesData3[Region], "Abuja", SalesData3[Revenue]) -> 178000
I19: Lagos Revenue | J19: =SUMIF(SalesData3[Region],"Lagos",SalesData3[Revenue]) -> 78000
I20: Mouse Revenue | J20: =SUMIF(SalesData3[Product], "mouse", SalesData3[Revenue]) -> 55000
I21: Mouse rev. from Abj | J21: =SUMIFS(SalesData3[Revenue],SalesData3[Product],"mouse",SalesData3[Region], "abuja" ) -> 10000
I22: No. of cash payment | J22: =COUNTIF(SalesData3[Payment Method], "cash") -> 4
I23: No. of Lagos Orders | J23: =COUNTIF(SalesData3[Region], "lagos") -> 6
I24: No. of card payments | J24: =COUNTIF(SalesData3[Payment Method], "card") -> 5
I25: Abuja card payments | J25: =COUNTIFS(SalesData3[Region], "Abuja", SalesData3[Payment Method], "Card") -> 5

Sheet anaylsis
A1: Order ID | B1: Quantity | C1: Unit Price | D1: Revenue
A2: ORD001 | B2: 2 | C2: 15000 | D2: =B2*C2 -> 30000
A3: ORD002 | B3: 3 | C3: 5000 | D3: =B3*C3 -> 15000
A4: ORD003 | B4: 1 | C4: 12000 | D4: =B4*C4 -> 12000
A5: ORD004 | B5: 1 | C5: 15000 | D5: =B5*C5 -> 15000
A6: ORD005 | B6: 2 | C6: 18000 | D6: =B6*C6 -> 36000
A7: ORD006 | B7: 5 | C7: 3000 | D7: =B7*C7 -> 15000
A8: ORD007 | B8: 2 | C8: 5000 | D8: =B8*C8 -> 10000
A9: ORD008 | B9: 1 | C9: 12000 | D9: =B9*C9 -> 12000
A10: ORD009 | C10: 18000 | D10: =B10*C10 -> 0
A11: ORD010 | B11: 2 | C11: 15000 | D11: =B11*C11 -> 30000
A12: ORD011 | B12: 4 | C12: 5000 | D12: =B12*C12 -> 20000
A13: ORD012 | B13: 3 | C13: 3000 | D13: =B13*C13 -> 9000
A14: ORD013 | B14: 2 | C14: 12000 | D14: =B14*C14 -> 24000
A15: ORD014 | B15: 1 | C15: 18000 | D15: =B15*C15 -> 18000
A16: ORD015 | B16: 2 | C16: 5000 | D16: =B16*C16 -> 10000
B17: =SUM(B2:B16) -> 31 | C17: sum | D17: =SUM(Table5[Revenue]) -> 256000
C18: average | D18: =AVERAGE(Table5[Revenue]) -> 17066.667
C19: max | D19: =MAX(Table5[Revenue]) -> 36000
C20: min | D20: =MIN(Table5[Revenue]) -> 0

Sheet price list
A1: Product | B1: Unit Price
A2: Laptop bag | B2: 15000
A3: Mouse | B3: 5000
A4: Keyboard | B4: 12000
A5: Headphones | B5: 18000
A6: USB Cable | B6: 3000

Sheet pivot analysis
A3: Row Labels | B3: Sum of Revenue
A4: Headphones | B4: 54000
A5: Keyboard | B5: 48000
A6: Laptop bag | B6: 75000
A7: Mouse | B7: 55000
A8: USB Cable | B8: 24000
A9: Grand Total | B9: 256000
A11: Row Labels | B11: Count of Order ID
A12: Card | B12: 5
A13: Cash | B13: 4
A14: Transfer | B14: 6
A15: Grand Total | B15: 15
A17: Row Labels | B17: Sum of Revenue
A18: Card | B18: 132000
A19: Cash | B19: 52000
A20: Transfer | B20: 72000
A21: Grand Total | B21: 256000

Sheet analysis notes
A1: Sales Analysis Findings
A3: Dataset: | D3: Cleaned sales practice dataset
A5: Total recorded revenue: | D5: NGN 256,000 across 15 unique orders
A7: Regional performance: | D7: Abuja generated ₦178,000, while Lagos generated ₦78,000.
A9: Product performance: | D9: Laptop Bag generated the highest revenue at ₦75,000. USB Cable generated the lowest at ₦24,000.
A12: Payment methods: | D12: Card generated the highest revenue at ₦132,000. Transfer had the highest number of orders, with 6 transactions.
A15: Data-quality limitation: | D15: One order, ORD009, has a missing quantity. Its revenue is excluded from the calculated total, so the true total revenue may be higher.
A18: Next investigation: | D18: Examine average order value by payment method and investigate the missing quantity before drawing stronger conclusions about customer behaviour.

Sheet sales summary
A1: Sales summary
A3: Metric | B3: Result
A4: Total revenue | B4: =SUM(SalesData[Revenue]) -> 256000
A5: Total quantity sold | B5: =SUM(SalesData[Quantity]) -> 31
A6: Number of cash orders | B6: =COUNTIF(SalesData[Payment Method], "cash") -> 4
A7: Number of lagos orders | B7: =COUNTIF(SalesData[Region],"lagos") -> 6
A8: Abuja revenue | B8: =SUMIF(SalesData[Region],"abuja", SalesData[Revenue]) -> 178000

Sheet KPI analysis
A1: Sales KPI Analysis
A3: KPI | B3: Result
A4: Total recorded revenue | B4: =SUM(SalesData[Revenue]) -> 256000
A5: Total unique orders | B5: =COUNTA(SalesData[Order ID]) -> 15
A6: Orders with known revenue | B6: =COUNT(SalesData[Revenue]) -> 14
A7: Average recorded revenue per known order | B7: =AVERAGE(SalesData[Revenue]) -> 18285.714
A8: Total quantity sold | B8: =SUM(SalesData[Quantity]) -> 31
A10: Average recorded revenue per known order | B10: =AVERAGE(SalesData[Revenue]) -> 18285.714
A11: Orders with missing revenue | B11: =COUNTBLANK(SalesData[Revenue]) -> 1
A13: Revenue by payment method
A14: Payment method | B14: Revenue | C14: Revenue Contribution
A15: Cash | B15: =SUMIF(SalesData[Payment Method],A15,SalesData[Revenue]) -> 52000 | C15: =B15/$B$4 -> 0.203125
A16: Card | B16: =SUMIF(SalesData[Payment Method],A16,SalesData[Revenue]) -> 132000 | C16: =B16/$B$4 -> 0.515625
A17: Transfer | B17: =SUMIF(SalesData[Payment Method],A17,SalesData[Revenue]) -> 72000 | C17: =B17/$B$4 -> 0.28125
A18: Total | B18: =SUM(B15:B17) -> 256000 | C18: =SUM(C15:C17) -> 1

Sheet KPI notes
A1: Sales KPI Analysis
A3: Total recorded revenue | D3: NGN 256,000 across 15 unique orders
A4: Orders with known revenue | D4: 14 orders have recorded revenue. One order, ORD009, has a missing quantity and therefore no calculated revenue
A6: Average recorded revenue per known order | D6: ₦18,285.71. This average is based on 14 orders with known revenue, not all 15 orders.
A8: Total quantity sold: | D8: 31 units recorded across orders with known quantities.
A9: Revenue contribution by payment method: | D9: Cash: ₦52,000 (20.31%)
D10: Card: ₦132,000 (51.56%)
D11: Transfer: ₦72,000 (28.13%)
A12: Key finding: | D12: Card payments contributed the largest share of recorded revenue, at 51.56%. However, revenue contribution alone does not establish which payment method generates the most profit.
A15: Data-quality limitation: | D15: ORD009 has a missing quantity. Its revenue is excluded from the total, so the true total revenue and average revenue across all orders may be higher or otherwise different.
A18: Recommended next step: | D18: Investigate the missing quantity in ORD009 and analyse costs and profit by payment method before making stronger business recommendations.

Sheet data quality
A1: DATA QUALITY CHECKS
A3: Check | B3: Result
A4: Total Orders | B4: =COUNTA(SalesData[Order ID]) -> 15
A5: Missing quantities | B5: =COUNTBLANK(SalesData[Quantity]) -> 1
A6: Missing revenue values | B6: =COUNTBLANK(SalesData[Revenue]) -> 1
A7: Duplicate order IDs | B7: =COUNTIF(SalesData3[Duplicate Check], ">1") -> 0
A8: Invalid payment methods | B8: =COUNTIF(SalesData3[Payment Check], "Invalid") -> 0
